easy_tools/__init__.py
easy_tools/doublet_sum_occurrence.py
easy_tools/triplet_sum_occurrence.py
easy_tools-0.1.dist-info/LICENSE
easy_tools-0.1.dist-info/METADATA
easy_tools-0.1.dist-info/WHEEL
easy_tools-0.1.dist-info/top_level.txt
easy_tools-0.1.dist-info/RECORD
