Metadata-Version: 2.1
Name: easy-tools
Version: 0.1
Summary: easy_tools is a package that helps to perform easy operations on iterables with less time complexity
Home-page: https://github.com/jayanthsai1998/EasyTools
Author: Jayanth Sai
Author-email: jayanthsai1998@gmail.com
License: MIT
Platform: UNKNOWN
